mitchell_portal_gun/__init__.py
mitchell_portal_gun/__main__.py
mitchell_portal_gun/main.py
mitchell_portal_gun-0.2.0.dist-info/entry_points.txt
mitchell_portal_gun-0.2.0.dist-info/WHEEL
mitchell_portal_gun-0.2.0.dist-info/METADATA
mitchell_portal_gun-0.2.0.dist-info/RECORD
