Metadata-Version: 2.1
Name: mitchell-portal-gun
Version: 0.2.0
Summary: 
Author: Mitchell Mirano
Author-email: mitchellmirano25@gmail.com
Requires-Python: >=3.10,<4.0
Classifier: Programming Language :: Python :: 3
Classifier: Programming Language :: Python :: 3.10
Requires-Dist: typer[all] (>=0.6.1,<0.7.0)
